fruitfly/__init__.py
fruitfly/__main__.py
fruitfly/fruitfly.py
fruitfly/module.py
fruitfly-0.1.6.dist-info/licenses/LICENSE
fruitfly-0.1.6.dist-info/METADATA
fruitfly-0.1.6.dist-info/WHEEL
fruitfly-0.1.6.dist-info/top_level.txt
fruitfly-0.1.6.dist-info/RECORD
