Metadata-Version: 2.4
Name: fruitfly
Version: 0.1.6
Summary: Modular event-driven framework.
Home-page: https://github.com/derpston/fruitfly
Author: Derp Ston
Author-email: derpston+pypi@sleepygeek.org
License-File: LICENSE
Requires-Dist: PyYAML
Dynamic: author
Dynamic: author-email
Dynamic: description
Dynamic: home-page
Dynamic: license-file
Dynamic: requires-dist
Dynamic: summary
